{
  "meta": {
    "same_name": {
      "region": [],
      "keyword": "잠실역 2호선 8번출구",
      "selected_region": ""
    },
    "pageable_count": 3,
    "total_count": 3,
    "is_end": true
  },
  "documents": [
    {
      "place_url": "http://place.map.daum.net/8530682",
      "category_group_name": "",
      "place_name": "잠실역 2호선 8번출구",
      "distance": "",
      "address_name": "서울 송파구 신천동",
      "road_address_name": "",
      "id": "8530682",
      "phone": "",
      "category_group_code": "",
      "category_name": "교통,수송 > 지하철,전철",
      "x": "127.10105349781466",
      "y": "37.51383016414731"
    },
    {
      "place_url": "http://place.map.daum.net/22905854",
      "category_group_name": "",
      "place_name": "잠실새내역 2호선 8번출구",
      "distance": "",
      "address_name": "서울 송파구 잠실동",
      "road_address_name": "",
      "id": "22905854",
      "phone": "",
      "category_group_code": "",
      "category_name": "교통,수송 > 지하철,전철",
      "x": "127.08768163388407",
      "y": "37.51181523433984"
    },
    {
      "place_url": "http://place.map.daum.net/8076145",
      "category_group_name": "",
      "place_name": "종합운동장역 2호선 8번출구",
      "distance": "",
      "address_name": "서울 송파구 잠실동",
      "road_address_name": "",
      "id": "8076145",
      "phone": "",
      "category_group_code": "",
      "category_name": "교통,수송 > 지하철,전철",
      "x": "127.0745928693402",
      "y": "37.511733956676224"
    }
  ]
}