{
  "meta": {
    "same_name": {
      "region": [],
      "keyword": "중랑역 경의중앙선 3번출구",
      "selected_region": ""
    },
    "pageable_count": 1,
    "total_count": 1,
    "is_end": true
  },
  "documents": [
    {
      "place_url": "http://place.map.daum.net/8519097",
      "category_group_name": "",
      "place_name": "중랑역 경의중앙선 3번출구",
      "distance": "",
      "address_name": "서울 중랑구 중화동",
      "road_address_name": "",
      "id": "8519097",
      "phone": "",
      "category_group_code": "",
      "category_name": "교통,수송 > 지하철,전철",
      "x": "127.07643146139034",
      "y": "37.59488702000555"
    }
  ]
}