{
  "gateList": [
    {
      "beginRow": null,
      "endRow": null,
      "curPage": null,
      "pageRow": null,
      "totalCount": 2,
      "rowNum": 1,
      "selectedCount": 2,
      "statnId": "1009000901",
      "statnNm": "개화",
      "ectrcNo": "1",
      "subwayId": "1009",
      "subwayNm": "9호선",
      "ectrcCnt": "2",
      "cfrBuild": "개화119,개화동방면,우리들병원,개화파출소",
      "subwayXcnts": null,
      "subwayYcnts": null,
      "ectrcId": null
    },
    {
      "beginRow": null,
      "endRow": null,
      "curPage": null,
      "pageRow": null,
      "totalCount": 2,
      "rowNum": 2,
      "selectedCount": 2,
      "statnId": "1009000901",
      "statnNm": "개화",
      "ectrcNo": "2",
      "subwayId": "1009",
      "subwayNm": "9호선",
      "ectrcCnt": "2",
      "cfrBuild": "개화119,개화동방면,우리들병원,개화파출소",
      "subwayXcnts": null,
      "subwayYcnts": null,
      "ectrcId": null
    }
  ],
  "errorMessage": {
    "status": 200,
    "code": "INFO-000",
    "message": "정상 처리되었습니다.",
    "link": "",
    "developerMessage": "",
    "total": 2
  }
}