{
  "gateList": [
    {
      "beginRow": null,
      "endRow": null,
      "curPage": null,
      "pageRow": null,
      "totalCount": 4,
      "rowNum": 1,
      "selectedCount": 4,
      "statnId": "1003000320",
      "statnNm": "구파발",
      "ectrcNo": "1",
      "subwayId": "1003",
      "subwayNm": "3호선",
      "ectrcCnt": "4",
      "cfrBuild": "구파발폭포,북한산방면,진관중학교,은평뉴타운 1지구,3-1지구,진관고등학교,복합환승센터(환승주차장),감사원 교육원행 버스 타는 곳,은빛초등학교",
      "subwayXcnts": null,
      "subwayYcnts": null,
      "ectrcId": null
    },
    {
      "beginRow": null,
      "endRow": null,
      "curPage": null,
      "pageRow": null,
      "totalCount": 4,
      "rowNum": 2,
      "selectedCount": 4,
      "statnId": "1003000320",
      "statnNm": "구파발",
      "ectrcNo": "2",
      "subwayId": "1003",
      "subwayNm": "3호선",
      "ectrcCnt": "4",
      "cfrBuild": "기자촌방면,신도초등학교,은평메디텍고등학교,진관동주민센터,은평뉴타운2지구, 3-2지구,은진초등학교",
      "subwayXcnts": null,
      "subwayYcnts": null,
      "ectrcId": null
    },
    {
      "beginRow": null,
      "endRow": null,
      "curPage": null,
      "pageRow": null,
      "totalCount": 4,
      "rowNum": 3,
      "selectedCount": 4,
      "statnId": "1003000320",
      "statnNm": "구파발",
      "ectrcNo": "3",
      "subwayId": "1003",
      "subwayNm": "3호선",
      "ectrcCnt": "4",
      "cfrBuild": "연신내방면,박석고개,신도고등학교,은평소방서",
      "subwayXcnts": null,
      "subwayYcnts": null,
      "ectrcId": null
    },
    {
      "beginRow": null,
      "endRow": null,
      "curPage": null,
      "pageRow": null,
      "totalCount": 4,
      "rowNum": 4,
      "selectedCount": 4,
      "statnId": "1003000320",
      "statnNm": "구파발",
      "ectrcNo": "4",
      "subwayId": "1003",
      "subwayNm": "3호선",
      "ectrcCnt": "4",
      "cfrBuild": "통일로방면",
      "subwayXcnts": null,
      "subwayYcnts": null,
      "ectrcId": null
    }
  ],
  "errorMessage": {
    "status": 200,
    "code": "INFO-000",
    "message": "정상 처리되었습니다.",
    "link": "",
    "developerMessage": "",
    "total": 4
  }
}