{
  "gateList": [
    {
      "beginRow": null,
      "endRow": null,
      "curPage": null,
      "pageRow": null,
      "totalCount": 2,
      "rowNum": 1,
      "selectedCount": 2,
      "statnId": "1063075127",
      "statnNm": "도심",
      "ectrcNo": "1",
      "subwayId": "1063",
      "subwayNm": "경의중앙선",
      "ectrcCnt": "2",
      "cfrBuild": "덕소중학교,도심초등학교,도곡리",
      "subwayXcnts": null,
      "subwayYcnts": null,
      "ectrcId": null
    },
    {
      "beginRow": null,
      "endRow": null,
      "curPage": null,
      "pageRow": null,
      "totalCount": 2,
      "rowNum": 2,
      "selectedCount": 2,
      "statnId": "1063075127",
      "statnNm": "도심",
      "ectrcNo": "2",
      "subwayId": "1063",
      "subwayNm": "경의중앙선",
      "ectrcCnt": "2",
      "cfrBuild": "남양주 도곡초등학교,남양주 도곡초등학교 병설 유치원,덕소고등학교,도곡근린공원,도곡교,덕소강변대교,와부119안전센터방면",
      "subwayXcnts": null,
      "subwayYcnts": null,
      "ectrcId": null
    }
  ],
  "errorMessage": {
    "status": 200,
    "code": "INFO-000",
    "message": "정상 처리되었습니다.",
    "link": "",
    "developerMessage": "",
    "total": 2
  }
}