{
  "gateList": [
    {
      "beginRow": null,
      "endRow": null,
      "curPage": null,
      "pageRow": null,
      "totalCount": 7,
      "rowNum": 1,
      "selectedCount": 7,
      "statnId": "1002000235",
      "statnNm": "문래",
      "ectrcNo": "1",
      "subwayId": "1002",
      "subwayNm": "2호선",
      "ectrcCnt": "7",
      "cfrBuild": "공원한신아파트,구립영등포노인종합복지관,국화아파트,문래2동,문래공원,중앙고용정보원,한국고용정보원,대림아파트,우정아파트",
      "subwayXcnts": null,
      "subwayYcnts": null,
      "ectrcId": null
    },
    {
      "beginRow": null,
      "endRow": null,
      "curPage": null,
      "pageRow": null,
      "totalCount": 7,
      "rowNum": 2,
      "selectedCount": 7,
      "statnId": "1002000235",
      "statnNm": "문래",
      "ectrcNo": "2",
      "subwayId": "1002",
      "subwayNm": "2호선",
      "ectrcCnt": "7",
      "cfrBuild": "공원한신아파트,문래동3가,LG하이프라자",
      "subwayXcnts": null,
      "subwayYcnts": null,
      "ectrcId": null
    },
    {
      "beginRow": null,
      "endRow": null,
      "curPage": null,
      "pageRow": null,
      "totalCount": 7,
      "rowNum": 3,
      "selectedCount": 7,
      "statnId": "1002000235",
      "statnNm": "문래",
      "ectrcNo": "3",
      "subwayId": "1002",
      "subwayNm": "2호선",
      "ectrcCnt": "7",
      "cfrBuild": "문래미원아파트,문래청소년수련관(YMCA),문래초등학교,신동아아파트,영등포구청방면,한전영등포지점,한전,영문초등학교,교보생명,GS홈쇼핑,신동아아파트,미원아파트",
      "subwayXcnts": null,
      "subwayYcnts": null,
      "ectrcId": null
    },
    {
      "beginRow": null,
      "endRow": null,
      "curPage": null,
      "pageRow": null,
      "totalCount": 7,
      "rowNum": 4,
      "selectedCount": 7,
      "statnId": "1002000235",
      "statnNm": "문래",
      "ectrcNo": "4",
      "subwayId": "1002",
      "subwayNm": "2호선",
      "ectrcCnt": "7",
      "cfrBuild": "당산동1가,당산진로아파트,영일시장,영등포소방서,양화중학교,홈플러스,CGV,벽산아파트,코오롱아파트",
      "subwayXcnts": null,
      "subwayYcnts": null,
      "ectrcId": null
    },
    {
      "beginRow": null,
      "endRow": null,
      "curPage": null,
      "pageRow": null,
      "totalCount": 7,
      "rowNum": 5,
      "selectedCount": 7,
      "statnId": "1002000235",
      "statnNm": "문래",
      "ectrcNo": "5",
      "subwayId": "1002",
      "subwayNm": "2호선",
      "ectrcCnt": "7",
      "cfrBuild": "문래 LG 빌리지,문래동3가,문래동주민센터,로데오거리",
      "subwayXcnts": null,
      "subwayYcnts": null,
      "ectrcId": null
    },
    {
      "beginRow": null,
      "endRow": null,
      "curPage": null,
      "pageRow": null,
      "totalCount": 7,
      "rowNum": 6,
      "selectedCount": 7,
      "statnId": "1002000235",
      "statnNm": "문래",
      "ectrcNo": "6",
      "subwayId": "1002",
      "subwayNm": "2호선",
      "ectrcCnt": "7",
      "cfrBuild": "문래 LG 빌리지,기업은향,문래자이아파트",
      "subwayXcnts": null,
      "subwayYcnts": null,
      "ectrcId": null
    },
    {
      "beginRow": null,
      "endRow": null,
      "curPage": null,
      "pageRow": null,
      "totalCount": 7,
      "rowNum": 7,
      "selectedCount": 7,
      "statnId": "1002000235",
      "statnNm": "문래",
      "ectrcNo": "7",
      "subwayId": "1002",
      "subwayNm": "2호선",
      "ectrcCnt": "7",
      "cfrBuild": "기업은행문래동지점,문래1동사무소,문래동3가,문래동우체국,영등포,영등포초등학교,구로세무서,영등포등기소,에이스타운(건설)",
      "subwayXcnts": null,
      "subwayYcnts": null,
      "ectrcId": null
    }
  ],
  "errorMessage": {
    "status": 200,
    "code": "INFO-000",
    "message": "정상 처리되었습니다.",
    "link": "",
    "developerMessage": "",
    "total": 7
  }
}